pyfora/Connection.py
pyfora/DownloadPolicy.py
pyfora/Exceptions.py
pyfora/Executor.py
pyfora/Future.py
pyfora/ModuleDirectoryStructure.py
pyfora/NamedSingletons.py
pyfora/ObjectConverter.py
pyfora/ObjectRegistry.py
pyfora/PureImplementationMapping.py
pyfora/PureImplementationMappings.py
pyfora/PyAbortSingletons.py
pyfora/PyObjectWalker.py
pyfora/PyforaInspect.py
pyfora/PyforaWithBlock.py
pyfora/PythonObjectRehydrator.py
pyfora/RemotePythonObject.py
pyfora/SocketIoJsonInterface.py
pyfora/StdinCache.py
pyfora/StronglyConnectedComponents.py
pyfora/SubscribableWebObjects.py
pyfora/TypeDescription.py
pyfora/WithBlockExecutor.py
pyfora/__init__.py
pyfora/_version.py
pyfora/pandas_util.py
pyfora/unique.py
pyfora/algorithms/LinearRegression.py
pyfora/algorithms/__init__.py
pyfora/algorithms/logistic/BinaryLogisticRegressionFitter.py
pyfora/algorithms/logistic/BinaryLogisticRegressionModel.py
pyfora/algorithms/logistic/FullRankMajorizationSolver.py
pyfora/algorithms/logistic/Solver.py
pyfora/algorithms/logistic/TrustRegionConjugateGradientSolver.py
pyfora/algorithms/logistic/__init__.py
pyfora/algorithms/regressionTrees/AdditiveRegressionTree.py
pyfora/algorithms/regressionTrees/Base.py
pyfora/algorithms/regressionTrees/BinaryClassificationModel.py
pyfora/algorithms/regressionTrees/GradientBoostedClassifierBuilder.py
pyfora/algorithms/regressionTrees/GradientBoostedRegressorBuilder.py
pyfora/algorithms/regressionTrees/RegressionModel.py
pyfora/algorithms/regressionTrees/RegressionTree.py
pyfora/algorithms/regressionTrees/__init__.py
pyfora/algorithms/regressionTrees/losses.py
pyfora/aws/Cluster.py
pyfora/aws/Launcher.py
pyfora/aws/__init__.py
pyfora/aws/pyfora_aws.py
pyfora/fora/purePython/AbortExceptionBase.fora
pyfora/fora/purePython/AssertionError.fora
pyfora/fora/purePython/AssociativeReduce.fora
pyfora/fora/purePython/AttributeError.fora
pyfora/fora/purePython/BoolType.fora
pyfora/fora/purePython/DictType.fora
pyfora-0.5.10.dist-info/DESCRIPTION.rst
pyfora-0.5.10.dist-info/METADATA
pyfora-0.5.10.dist-info/RECORD
pyfora-0.5.10.dist-info/WHEEL
pyfora-0.5.10.dist-info/entry_points.txt
pyfora-0.5.10.dist-info/metadata.json
pyfora-0.5.10.dist-info/top_level.txt
