Metadata-Version: 2.0
Name: pyfora
Version: 0.5.10
Summary: A library for parallel execution of Python code in the Ufora runtime
Home-page: http://www.ufora.com/
Author: Ufora Inc.
Author-email: info@ufora.com
License: Apache
Keywords: ufora fora parallel remote data-science machine-learning
Platform: UNKNOWN
Classifier: Development Status :: 3 - Alpha
Classifier: Environment :: Console
Classifier: Intended Audience :: Science/Research
Classifier: License :: OSI Approved :: Apache Software License
Classifier: Operating System :: OS Independent
Classifier: Programming Language :: Python :: 2.7
Classifier: Topic :: Scientific/Engineering
Requires-Dist: futures
Requires-Dist: numpy
Requires-Dist: socketIO-client (>=0.6.5)
Requires-Dist: websocket-client (==0.37.0)
Requires-Dist: wsaccel
